PyFunceble/__init__.py
PyFunceble/exceptions.py
PyFunceble/facility.py
PyFunceble/factory.py
PyFunceble/logger.py
PyFunceble/sessions.py
PyFunceble/storage.py
PyFunceble/storage_facility.py
PyFunceble/checker/__init__.py
PyFunceble/checker/base.py
PyFunceble/checker/complex_json_encoder.py
PyFunceble/checker/params_base.py
PyFunceble/checker/status_base.py
PyFunceble/checker/availability/__init__.py
PyFunceble/checker/availability/base.py
PyFunceble/checker/availability/domain.py
PyFunceble/checker/availability/domain_and_ip.py
PyFunceble/checker/availability/ip.py
PyFunceble/checker/availability/params.py
PyFunceble/checker/availability/status.py
PyFunceble/checker/availability/url.py
PyFunceble/checker/availability/extras/__init__.py
PyFunceble/checker/availability/extras/base.py
PyFunceble/checker/availability/extras/dns.py
PyFunceble/checker/availability/extras/etoxic.py
PyFunceble/checker/availability/extras/external.py
PyFunceble/checker/availability/extras/parked.py
PyFunceble/checker/availability/extras/rules.py
PyFunceble/checker/availability/extras/subject_switch.py
PyFunceble/checker/reputation/__init__.py
PyFunceble/checker/reputation/base.py
PyFunceble/checker/reputation/domain.py
PyFunceble/checker/reputation/domain_and_ip.py
PyFunceble/checker/reputation/ip.py
PyFunceble/checker/reputation/params.py
PyFunceble/checker/reputation/status.py
PyFunceble/checker/reputation/url.py
PyFunceble/checker/syntax/__init__.py
PyFunceble/checker/syntax/base.py
PyFunceble/checker/syntax/domain.py
PyFunceble/checker/syntax/domain_and_ip.py
PyFunceble/checker/syntax/domain_base.py
PyFunceble/checker/syntax/ip.py
PyFunceble/checker/syntax/ipv4.py
PyFunceble/checker/syntax/ipv6.py
PyFunceble/checker/syntax/params.py
PyFunceble/checker/syntax/second_lvl_domain.py
PyFunceble/checker/syntax/status.py
PyFunceble/checker/syntax/subdomain.py
PyFunceble/checker/syntax/url.py
PyFunceble/checker/utils/__init__.py
PyFunceble/checker/utils/whois.py
PyFunceble/cli/__init__.py
pyfunceble-4.3.1.dist-info/licenses/LICENSE
pyfunceble-4.3.1.dist-info/METADATA
pyfunceble-4.3.1.dist-info/WHEEL
pyfunceble-4.3.1.dist-info/entry_points.txt
pyfunceble-4.3.1.dist-info/top_level.txt
pyfunceble-4.3.1.dist-info/RECORD
