Metadata-Version: 2.4
Name: PyFunceble
Version: 4.3.1
Summary: The tool to check the availability or syntax of domain, IP or URL.
Home-page: https://github.com/funilrys/PyFunceble
Author: funilrys
Author-email: contact@funilrys.com
License: Apache 2.0
Project-URL: Documentation, https://docs.pyfunceble.com
Project-URL: Funding, https://github.com/sponsors/funilrys
Project-URL: Source, https://github.com/funilrys/PyFunceble/tree/master
Project-URL: Tracker, https://github.com/funilrys/PyFunceble/issues
Keywords: PyFunceble,syntax-checker,reputation-checker,availability-checker
Platform: any
Classifier: Environment :: Console
Classifier: Topic :: Internet
Classifier: Development Status :: 5 - Production/Stable
Classifier: Intended Audience :: Developers
Classifier: Programming Language :: Python
Classifier: Programming Language :: Python :: 3
Requires-Python: >=3.10, <4
License-File: LICENSE
Requires-Dist: inflection
Requires-Dist: python-box[all]~=7.3.2
Requires-Dist: pyfunceble-process-manager==1.0.10
Requires-Dist: shtab
Requires-Dist: colorama
Requires-Dist: setuptools>=65.5.1
Requires-Dist: SQLAlchemy~=2.0
Requires-Dist: PyYAML
Requires-Dist: PyMySQL
Requires-Dist: python-dotenv
Requires-Dist: packaging
Requires-Dist: domain2idna~=1.12.0
Requires-Dist: dnspython[DOH]~=2.8.0
Requires-Dist: alembic
Requires-Dist: requests[socks]<3
Provides-Extra: docs
Requires-Dist: pymdown-extensions~=10.9; extra == "docs"
Requires-Dist: zipp>=3.19.1; extra == "docs"
Requires-Dist: mkdocs-git-authors-plugin~=0.9; extra == "docs"
Requires-Dist: mkdocs-git-revision-date-localized-plugin~=1.2; extra == "docs"
Requires-Dist: mkdocs-material~=9.5; extra == "docs"
Requires-Dist: mkdocs-section-index~=0.3; extra == "docs"
Requires-Dist: mkdocs~=1.5; extra == "docs"
Requires-Dist: mkdocs-literate-nav~=0.6; extra == "docs"
Requires-Dist: mkdocs-gen-files~=0.5; extra == "docs"
Requires-Dist: mkdocs-macros-plugin~=1.2; extra == "docs"
Requires-Dist: mkdocstrings[python]~=1.0; extra == "docs"
Provides-Extra: dev
Requires-Dist: flake8; extra == "dev"
Requires-Dist: pylint; extra == "dev"
Requires-Dist: isort; extra == "dev"
Requires-Dist: black; extra == "dev"
Requires-Dist: bandit; extra == "dev"
Provides-Extra: test
Requires-Dist: tox; extra == "test"
Requires-Dist: coverage; extra == "test"
Provides-Extra: psql
Requires-Dist: inflection; extra == "psql"
Requires-Dist: python-box[all]~=7.3.2; extra == "psql"
Requires-Dist: pyfunceble-process-manager==1.0.10; extra == "psql"
Requires-Dist: shtab; extra == "psql"
Requires-Dist: colorama; extra == "psql"
Requires-Dist: setuptools>=65.5.1; extra == "psql"
Requires-Dist: SQLAlchemy~=2.0; extra == "psql"
Requires-Dist: PyYAML; extra == "psql"
Requires-Dist: PyMySQL; extra == "psql"
Requires-Dist: python-dotenv; extra == "psql"
Requires-Dist: packaging; extra == "psql"
Requires-Dist: domain2idna~=1.12.0; extra == "psql"
Requires-Dist: dnspython[DOH]~=2.8.0; extra == "psql"
Requires-Dist: alembic; extra == "psql"
Requires-Dist: requests[socks]<3; extra == "psql"
Requires-Dist: psycopg2; extra == "psql"
Provides-Extra: psql-binary
Requires-Dist: inflection; extra == "psql-binary"
Requires-Dist: python-box[all]~=7.3.2; extra == "psql-binary"
Requires-Dist: pyfunceble-process-manager==1.0.10; extra == "psql-binary"
Requires-Dist: shtab; extra == "psql-binary"
Requires-Dist: colorama; extra == "psql-binary"
Requires-Dist: setuptools>=65.5.1; extra == "psql-binary"
Requires-Dist: SQLAlchemy~=2.0; extra == "psql-binary"
Requires-Dist: PyYAML; extra == "psql-binary"
Requires-Dist: PyMySQL; extra == "psql-binary"
Requires-Dist: python-dotenv; extra == "psql-binary"
Requires-Dist: packaging; extra == "psql-binary"
Requires-Dist: domain2idna~=1.12.0; extra == "psql-binary"
Requires-Dist: dnspython[DOH]~=2.8.0; extra == "psql-binary"
Requires-Dist: alembic; extra == "psql-binary"
Requires-Dist: requests[socks]<3; extra == "psql-binary"
Requires-Dist: psycopg2-binary; extra == "psql-binary"
Provides-Extra: postgresql
Requires-Dist: inflection; extra == "postgresql"
Requires-Dist: python-box[all]~=7.3.2; extra == "postgresql"
Requires-Dist: pyfunceble-process-manager==1.0.10; extra == "postgresql"
Requires-Dist: shtab; extra == "postgresql"
Requires-Dist: colorama; extra == "postgresql"
Requires-Dist: setuptools>=65.5.1; extra == "postgresql"
Requires-Dist: SQLAlchemy~=2.0; extra == "postgresql"
Requires-Dist: PyYAML; extra == "postgresql"
Requires-Dist: PyMySQL; extra == "postgresql"
Requires-Dist: python-dotenv; extra == "postgresql"
Requires-Dist: packaging; extra == "postgresql"
Requires-Dist: domain2idna~=1.12.0; extra == "postgresql"
Requires-Dist: dnspython[DOH]~=2.8.0; extra == "postgresql"
Requires-Dist: alembic; extra == "postgresql"
Requires-Dist: requests[socks]<3; extra == "postgresql"
Requires-Dist: psycopg2; extra == "postgresql"
Provides-Extra: postgresql-binary
Requires-Dist: inflection; extra == "postgresql-binary"
Requires-Dist: python-box[all]~=7.3.2; extra == "postgresql-binary"
Requires-Dist: pyfunceble-process-manager==1.0.10; extra == "postgresql-binary"
Requires-Dist: shtab; extra == "postgresql-binary"
Requires-Dist: colorama; extra == "postgresql-binary"
Requires-Dist: setuptools>=65.5.1; extra == "postgresql-binary"
Requires-Dist: SQLAlchemy~=2.0; extra == "postgresql-binary"
Requires-Dist: PyYAML; extra == "postgresql-binary"
Requires-Dist: PyMySQL; extra == "postgresql-binary"
Requires-Dist: python-dotenv; extra == "postgresql-binary"
Requires-Dist: packaging; extra == "postgresql-binary"
Requires-Dist: domain2idna~=1.12.0; extra == "postgresql-binary"
Requires-Dist: dnspython[DOH]~=2.8.0; extra == "postgresql-binary"
Requires-Dist: alembic; extra == "postgresql-binary"
Requires-Dist: requests[socks]<3; extra == "postgresql-binary"
Requires-Dist: psycopg2-binary; extra == "postgresql-binary"
Provides-Extra: full
Requires-Dist: tox; extra == "full"
Requires-Dist: colorama; extra == "full"
Requires-Dist: setuptools>=65.5.1; extra == "full"
Requires-Dist: SQLAlchemy~=2.0; extra == "full"
Requires-Dist: pylint; extra == "full"
Requires-Dist: PyMySQL; extra == "full"
Requires-Dist: mkdocs-material~=9.5; extra == "full"
Requires-Dist: coverage; extra == "full"
Requires-Dist: alembic; extra == "full"
Requires-Dist: mkdocs-git-authors-plugin~=0.9; extra == "full"
Requires-Dist: bandit; extra == "full"
Requires-Dist: python-box[all]~=7.3.2; extra == "full"
Requires-Dist: pyfunceble-process-manager==1.0.10; extra == "full"
Requires-Dist: mkdocs-git-revision-date-localized-plugin~=1.2; extra == "full"
Requires-Dist: PyYAML; extra == "full"
Requires-Dist: mkdocs-gen-files~=0.5; extra == "full"
Requires-Dist: domain2idna~=1.12.0; extra == "full"
Requires-Dist: requests[socks]<3; extra == "full"
Requires-Dist: inflection; extra == "full"
Requires-Dist: mkdocs~=1.5; extra == "full"
Requires-Dist: isort; extra == "full"
Requires-Dist: packaging; extra == "full"
Requires-Dist: mkdocs-macros-plugin~=1.2; extra == "full"
Requires-Dist: mkdocstrings[python]~=1.0; extra == "full"
Requires-Dist: pymdown-extensions~=10.9; extra == "full"
Requires-Dist: zipp>=3.19.1; extra == "full"
Requires-Dist: shtab; extra == "full"
Requires-Dist: flake8; extra == "full"
Requires-Dist: mkdocs-section-index~=0.3; extra == "full"
Requires-Dist: python-dotenv; extra == "full"
Requires-Dist: mkdocs-literate-nav~=0.6; extra == "full"
Requires-Dist: black; extra == "full"
Requires-Dist: dnspython[DOH]~=2.8.0; extra == "full"
Provides-Extra: all
Requires-Dist: tox; extra == "all"
Requires-Dist: colorama; extra == "all"
Requires-Dist: setuptools>=65.5.1; extra == "all"
Requires-Dist: SQLAlchemy~=2.0; extra == "all"
Requires-Dist: pylint; extra == "all"
Requires-Dist: PyMySQL; extra == "all"
Requires-Dist: mkdocs-material~=9.5; extra == "all"
Requires-Dist: coverage; extra == "all"
Requires-Dist: alembic; extra == "all"
Requires-Dist: mkdocs-git-authors-plugin~=0.9; extra == "all"
Requires-Dist: bandit; extra == "all"
Requires-Dist: python-box[all]~=7.3.2; extra == "all"
Requires-Dist: pyfunceble-process-manager==1.0.10; extra == "all"
Requires-Dist: mkdocs-git-revision-date-localized-plugin~=1.2; extra == "all"
Requires-Dist: PyYAML; extra == "all"
Requires-Dist: mkdocs-gen-files~=0.5; extra == "all"
Requires-Dist: domain2idna~=1.12.0; extra == "all"
Requires-Dist: requests[socks]<3; extra == "all"
Requires-Dist: psycopg2-binary; extra == "all"
Requires-Dist: inflection; extra == "all"
Requires-Dist: mkdocs~=1.5; extra == "all"
Requires-Dist: isort; extra == "all"
Requires-Dist: packaging; extra == "all"
Requires-Dist: mkdocs-macros-plugin~=1.2; extra == "all"
Requires-Dist: mkdocstrings[python]~=1.0; extra == "all"
Requires-Dist: pymdown-extensions~=10.9; extra == "all"
Requires-Dist: zipp>=3.19.1; extra == "all"
Requires-Dist: shtab; extra == "all"
Requires-Dist: flake8; extra == "all"
Requires-Dist: mkdocs-section-index~=0.3; extra == "all"
Requires-Dist: python-dotenv; extra == "all"
Requires-Dist: mkdocs-literate-nav~=0.6; extra == "all"
Requires-Dist: black; extra == "all"
Requires-Dist: dnspython[DOH]~=2.8.0; extra == "all"
Dynamic: author
Dynamic: author-email
Dynamic: classifier
Dynamic: description
Dynamic: description-content-type
Dynamic: home-page
Dynamic: keywords
Dynamic: license
Dynamic: license-file
Dynamic: platform
Dynamic: project-url
Dynamic: provides-extra
Dynamic: requires-dist
Dynamic: requires-python
Dynamic: summary
